[
  {
    "id": 1,
    "name": "Copa Pixel",
    "game": "FIFA 25",
    "date": "2025-07-15",
    "image": "https://via.placeholder.com/300x200?text=Copa+Pixel",
    "details": "Torneo online abierto para todos."
  },
  {
    "id": 2,
    "name": "Masters League",
    "game": "eFootball 25",
    "date": "2025-08-20",
    "image": "https://via.placeholder.com/300x200?text=Masters+League",
    "details": "Competencia por invitación para los mejores jugadores."
  },
  {
    "id": 3,
    "name": "Retro Challenge",
    "game": "PES 2021",
    "date": "2025-09-10",
    "image": "https://via.placeholder.com/300x200?text=Retro+Challenge",
    "details": "Revivimos la gloria de ediciones pasadas."
  }
]
